envutil/__init__.py
envutil/py.typed
envutil-0.2.4.dist-info/LICENSE
envutil-0.2.4.dist-info/WHEEL
envutil-0.2.4.dist-info/METADATA
envutil-0.2.4.dist-info/RECORD
