Metadata-Version: 2.1
Name: envutil
Version: 0.2.4
Summary: 
Author: Berke Arslan
Author-email: berke@kwilabs.com
Requires-Python: >=3.11,<4.0
Classifier: Programming Language :: Python :: 3
Classifier: Programming Language :: Python :: 3.11
Requires-Dist: python-dotenv (>=1.0.0,<2.0.0)
